[{"slug": "\u672b-2", "is_common": true, "tags": ["wanikani7"], "jlpt": ["jlpt-n3"], "japanese": [{"word": "\u672b", "reading": "\u3059\u3048"}], "senses": [{"english_definitions": ["end", "tip", "top"], "parts_of_speech": ["Noun"], "links": [], "tags": [], "restrictions": [], "see_also": [], "antonyms": [], "source": [], "info": []}, {"english_definitions": ["end (of the year, month, etc.)", "close"], "parts_of_speech": ["Noun"], "links": [], "tags": [], "restrictions": [], "see_also": [], "antonyms": [], "source": [], "info": []}, {"english_definitions": ["youngest child"], "parts_of_speech": ["Noun", "Noun which may take the genitive case particle 'no'"], "links": [], "tags": [], "restrictions": [], "see_also": ["\u672b\u3063\u5b50"], "antonyms": [], "source": [], "info": []}, {"english_definitions": ["descendants", "offspring", "posterity"], "parts_of_speech": ["Noun"], "links": [], "tags": [], "restrictions": [], "see_also": [], "antonyms": [], "source": [], "info": ["usu. \u301c\u306e\u672b"]}, {"english_definitions": ["future"], "parts_of_speech": ["Noun"], "links": [], "tags": [], "restrictions": [], "see_also": [], "antonyms": [], "source": [], "info": []}, {"english_definitions": ["(finally) after", "(at last) after", "at the end of"], "parts_of_speech": ["Adverb (fukushi)", "Noun"], "links": [], "tags": [], "restrictions": [], "see_also": [], "antonyms": [], "source": [], "info": ["as \u301c\u306e\u672b or \u301c\u3057\u305f\u672b"]}, {"english_definitions": ["trifles", "trivialities"], "parts_of_speech": ["Noun", "Noun which may take the genitive case particle 'no'"], "links": [], "tags": [], "restrictions": [], "see_also": [], "antonyms": [], "source": [], "info": []}, {"english_definitions": ["degenerate age"], "parts_of_speech": ["Noun"], "links": [], "tags": [], "restrictions": [], "see_also": [], "antonyms": [], "source": [], "info": []}], "attribution": {"jmdict": true, "jmnedict": false, "dbpedia": false}, "id": 3915, "result": null}, {"slug": "\u7aef", "is_common": true, "tags": ["wanikani27"], "jlpt": ["jlpt-n3"], "japanese": [{"word": "\u7aef", "reading": "\u306f\u3057"}, {"word": "\u7aef", "reading": "\u306f\u3058"}, {"word": "\u7aef", "reading": "\u306f\u306a"}], "senses": [{"english_definitions": ["end (e.g. of street)", "tip", "point", "edge", "margin"], "parts_of_speech": ["Noun"], "links": [], "tags": [], "restrictions": [], "see_also": [], "antonyms": [], "source": [], "info": []}, {"english_definitions": ["beginning", "start", "first"], "parts_of_speech": ["Noun"], "links": [], "tags": [], "restrictions": [], "see_also": [], "antonyms": [], "source": [], "info": []}, {"english_definitions": ["odds and ends", "scrap", "odd bit", "least"], "parts_of_speech": ["Noun"], "links": [], "tags": [], "restrictions": [], "see_also": [], "antonyms": [], "source": [], "info": []}], "attribution": {"jmdict": true, "jmnedict": false, "dbpedia": false}, "id": 3916, "result": null}, {"slug": "\u540c\u4e00", "is_common": true, "tags": [], "jlpt": ["jlpt-n3"], "japanese": [{"word": "\u540c\u4e00", "reading": "\u3069\u3046\u3044\u3064"}], "senses": [{"english_definitions": ["identical", "same", "one and the same", "equal"], "parts_of_speech": ["Noun which may take the genitive case particle 'no'", "Na-adjective (keiyodoshi)"], "links": [], "tags": [], "restrictions": [], "see_also": [], "antonyms": [], "source": [], "info": []}, {"english_definitions": ["fair", "equal treatment", "without discrimination"], "parts_of_speech": ["Noun which may take the genitive case particle 'no'", "Na-adjective (keiyodoshi)"], "links": [], "tags": [], "restrictions": [], "see_also": [], "antonyms": [], "source": [], "info": []}], "attribution": {"jmdict": true, "jmnedict": false, "dbpedia": false}, "id": 3917, "result": null}, {"slug": "\u7ae0", "is_common": true, "tags": [], "jlpt": ["jlpt-n3"], "japanese": [{"word": "\u7ae0", "reading": "\u3057\u3087\u3046"}], "senses": [{"english_definitions": ["chapter", "section"], "parts_of_speech": ["Noun"], "links": [], "tags": [], "restrictions": [], "see_also": [], "antonyms": [], "source": [], "info": []}, {"english_definitions": ["medal", "badge", "insignia"], "parts_of_speech": ["Noun", "Noun, used as a suffix"], "links": [], "tags": [], "restrictions": [], "see_also": [], "antonyms": [], "source": [], "info": []}], "attribution": {"jmdict": true, "jmnedict": false, "dbpedia": false}, "id": 3918, "result": null}, {"slug": "\u571f", "is_common": true, "tags": ["wanikani2"], "jlpt": ["jlpt-n3"], "japanese": [{"word": "\u571f", "reading": "\u3064\u3061"}, {"word": "\u5730", "reading": "\u3064\u3061"}, {"word": "\u5730", "reading": "\u3064\u3057"}], "senses": [{"english_definitions": ["earth", "soil", "dirt", "clay", "mud"], "parts_of_speech": ["Noun"], "links": [], "tags": [], "restrictions": [], "see_also": [], "antonyms": [], "source": [], "info": []}, {"english_definitions": ["the earth (historically, esp. as opposed to the heavens)", "the ground", "the land"], "parts_of_speech": ["Noun"], "links": [], "tags": [], "restrictions": [], "see_also": [], "antonyms": [], "source": [], "info": []}, {"english_definitions": ["low-quality torinoko-gami (containing mud)"], "parts_of_speech": ["Noun"], "links": [], "tags": [], "restrictions": [], "see_also": ["\u9ce5\u306e\u5b50\u7d19"], "antonyms": [], "source": [], "info": []}, {"english_definitions": ["(period of) refraining from construction in the direction of the god of the earth (in Onmy\u014dd\u014d)"], "parts_of_speech": ["Noun"], "links": [], "tags": [], "restrictions": [], "see_also": ["\u9670\u967d\u9053"], "antonyms": [], "source": [], "info": ["also written as \u72af\u571f, \u690e, \u69cc"]}], "attribution": {"jmdict": true, "jmnedict": false, "dbpedia": false}, "id": 3919, "result": null}, {"slug": "\u7dbf-1", "is_common": true, "tags": [], "jlpt": ["jlpt-n3"], "japanese": [{"word": "\u7dbf", "reading": "\u308f\u305f"}, {"word": "\u68c9", "reading": "\u308f\u305f"}, {"word": "\u8349\u7dbf", "reading": "\u308f\u305f"}, {"reading": "\u30ef\u30bf"}], "senses": [{"english_definitions": ["cotton plant (Gossypium spp.)"], "parts_of_speech": ["Noun"], "links": [], "tags": ["Usually written using kana alone"], "restrictions": [], "see_also": [], "antonyms": [], "source": [], "info": []}, {"english_definitions": ["batting", "wadding", "padding"], "parts_of_speech": ["Noun"], "links": [], "tags": [], "restrictions": [], "see_also": [], "antonyms": [], "source": [], "info": []}], "attribution": {"jmdict": true, "jmnedict": false, "dbpedia": false}, "id": 3920, "result": null}, {"slug": "\u7e01-2", "is_common": true, "tags": ["wanikani44"], "jlpt": ["jlpt-n3"], "japanese": [{"word": "\u7e01", "reading": "\u3075\u3061"}], "senses": [{"english_definitions": ["rim", "brim", "edge", "brink"], "parts_of_speech": ["Noun"], "links": [], "tags": [], "restrictions": [], "see_also": [], "antonyms": [], "source": [], "info": []}], "attribution": {"jmdict": true, "jmnedict": false, "dbpedia": false}, "id": 3921, "result": null}, {"slug": "\u5143-2", "is_common": false, "tags": [], "jlpt": ["jlpt-n3"], "japanese": [{"word": "\u5143", "reading": "\u3082\u3068"}, {"word": "\u65e7", "reading": "\u3082\u3068"}, {"word": "\u6545", "reading": "\u3082\u3068"}], "senses": [{"english_definitions": ["former", "ex-", "past", "one-time"], "parts_of_speech": ["Noun which may take the genitive case particle 'no'", "Noun, used as a prefix"], "links": [], "tags": [], "restrictions": [], "see_also": [], "antonyms": [], "source": [], "info": []}, {"english_definitions": ["earlier times", "the past", "previous state"], "parts_of_speech": ["Noun", "Noun which may take the genitive case particle 'no'"], "links": [], "tags": [], "restrictions": [], "see_also": [], "antonyms": [], "source": [], "info": []}, {"english_definitions": ["formerly", "previously", "originally", "before"], "parts_of_speech": ["Noun", "Adverb (fukushi)"], "links": [], "tags": [], "restrictions": [], "see_also": [], "antonyms": [], "source": [], "info": []}], "attribution": {"jmdict": true, "jmnedict": false, "dbpedia": false}, "id": 3922, "result": null}, {"slug": "\u4eba\u5de5", "is_common": true, "tags": ["wanikani1"], "jlpt": ["jlpt-n3"], "japanese": [{"word": "\u4eba\u5de5", "reading": "\u3058\u3093\u3053\u3046"}], "senses": [{"english_definitions": ["artificial", "man-made", "human work", "human skill", "artificiality"], "parts_of_speech": ["Noun", "Noun which may take the genitive case particle 'no'"], "links": [], "tags": [], "restrictions": [], "see_also": [], "antonyms": ["\u5929\u7136"], "source": [], "info": []}, {"english_definitions": ["Artificial"], "parts_of_speech": ["Wikipedia definition"], "links": [{"text": "Read \u201cArtificial\u201d on English Wikipedia", "url": "http://en.wikipedia.org/wiki/Artificial?oldid=484091497"}, {"text": "Read \u201c\u4eba\u5de5\u201d on Japanese Wikipedia", "url": "http://ja.wikipedia.org/wiki/\u4eba\u5de5?oldid=30505676"}], "tags": [], "restrictions": [], "see_also": [], "antonyms": [], "source": [], "info": [], "sentences": []}], "attribution": {"jmdict": true, "jmnedict": false, "dbpedia": "http://dbpedia.org/resource/Artificial"}, "id": 3923, "result": null}, {"slug": "\u67c4-1", "is_common": true, "tags": ["wanikani42"], "jlpt": ["jlpt-n3"], "japanese": [{"word": "\u67c4", "reading": "\u304c\u3089"}], "senses": [{"english_definitions": ["pattern", "design"], "parts_of_speech": ["Noun", "Noun, used as a suffix"], "links": [], "tags": [], "restrictions": [], "see_also": [], "antonyms": [], "source": [], "info": []}, {"english_definitions": ["body build", "figure", "physique"], "parts_of_speech": ["Noun"], "links": [], "tags": [], "restrictions": [], "see_also": [], "antonyms": [], "source": [], "info": []}, {"english_definitions": ["essential qualities", "character", "nature"], "parts_of_speech": ["Noun", "Noun, used as a suffix"], "links": [], "tags": [], "restrictions": [], "see_also": [], "antonyms": [], "source": [], "info": []}, {"english_definitions": ["appropriate to", "fitting of", "suitable for"], "parts_of_speech": ["Noun, used as a suffix"], "links": [], "tags": [], "restrictions": [], "see_also": [], "antonyms": [], "source": [], "info": []}], "attribution": {"jmdict": true, "jmnedict": false, "dbpedia": false}, "id": 3924, "result": null}, {"slug": "\u5bc6", "is_common": false, "tags": [], "jlpt": ["jlpt-n3"], "japanese": [{"word": "\u5bc6", "reading": "\u307f\u3064"}], "senses": [{"english_definitions": ["dense", "thick", "crowded"], "parts_of_speech": ["Na-adjective (keiyodoshi)", "Noun"], "links": [], "tags": [], "restrictions": [], "see_also": [], "antonyms": ["\u758e \u305d"], "source": [], "info": []}, {"english_definitions": ["close (relationship)", "intimate"], "parts_of_speech": ["Na-adjective (keiyodoshi)", "Noun"], "links": [], "tags": [], "restrictions": [], "see_also": [], "antonyms": [], "source": [], "info": []}, {"english_definitions": ["minute", "fine", "careful"], "parts_of_speech": ["Na-adjective (keiyodoshi)", "Noun"], "links": [], "tags": [], "restrictions": [], "see_also": [], "antonyms": [], "source": [], "info": []}, {"english_definitions": ["secret"], "parts_of_speech": ["Na-adjective (keiyodoshi)", "Noun"], "links": [], "tags": [], "restrictions": [], "see_also": [], "antonyms": [], "source": [], "info": []}, {"english_definitions": ["esoteric Buddhism", "secret Buddhist teachings"], "parts_of_speech": ["Noun"], "links": [], "tags": ["Buddhism", "Abbreviation"], "restrictions": [], "see_also": ["\u5bc6\u6559 \u307f\u3063\u304d\u3087\u3046"], "antonyms": [], "source": [], "info": []}], "attribution": {"jmdict": true, "jmnedict": false, "dbpedia": false}, "id": 3925, "result": null}, {"slug": "\u5800", "is_common": true, "tags": ["wanikani40"], "jlpt": ["jlpt-n3", "jlpt-n2"], "japanese": [{"word": "\u5800", "reading": "\u307b\u308a"}, {"word": "\u6fe0", "reading": "\u307b\u308a"}, {"word": "\u58d5", "reading": "\u307b\u308a"}], "senses": [{"english_definitions": ["moat", "fosse"], "parts_of_speech": ["Noun"], "links": [], "tags": [], "restrictions": [], "see_also": [], "antonyms": [], "source": [], "info": []}, {"english_definitions": ["canal", "ditch"], "parts_of_speech": ["Noun"], "links": [], "tags": [], "restrictions": [], "see_also": [], "antonyms": [], "source": [], "info": []}, {"english_definitions": ["Moat"], "parts_of_speech": ["Wikipedia definition"], "links": [{"text": "Read \u201cMoat\u201d on English Wikipedia", "url": "http://en.wikipedia.org/wiki/Moat?oldid=491489288"}, {"text": "Read \u201c\u5800\u201d on Japanese Wikipedia", "url": "http://ja.wikipedia.org/wiki/\u5800?oldid=42119357"}], "tags": [], "restrictions": [], "see_also": [], "antonyms": [], "source": [], "info": [], "sentences": []}], "attribution": {"jmdict": true, "jmnedict": false, "dbpedia": "http://dbpedia.org/resource/Moat"}, "id": 3926, "result": null}, {"slug": "\u66dc\u65e5", "is_common": true, "tags": ["wanikani16"], "jlpt": ["jlpt-n3"], "japanese": [{"word": "\u66dc\u65e5", "reading": "\u3088\u3046\u3073"}], "senses": [{"english_definitions": ["day of the week"], "parts_of_speech": ["Noun"], "links": [], "tags": [], "restrictions": [], "see_also": [], "antonyms": [], "source": [], "info": []}, {"english_definitions": ["Names of the days of the week"], "parts_of_speech": ["Wikipedia definition"], "links": [{"text": "Read \u201cNames of the days of the week\u201d on English Wikipedia", "url": "http://en.wikipedia.org/wiki/Names_of_the_days_of_the_week?oldid=495312378"}, {"text": "Read \u201c\u66dc\u65e5\u201d on Japanese Wikipedia", "url": "http://ja.wikipedia.org/wiki/\u66dc\u65e5?oldid=42035969"}], "tags": [], "restrictions": [], "see_also": [], "antonyms": [], "source": [], "info": [], "sentences": []}], "attribution": {"jmdict": true, "jmnedict": false, "dbpedia": "http://dbpedia.org/resource/Names_of_the_days_of_the_week"}, "id": 3927, "result": null}, {"slug": "\u677e", "is_common": true, "tags": ["wanikani14"], "jlpt": ["jlpt-n3"], "japanese": [{"word": "\u677e", "reading": "\u307e\u3064"}, {"reading": "\u30de\u30c4"}], "senses": [{"english_definitions": ["pine tree (Pinus spp.)"], "parts_of_speech": ["Noun"], "links": [], "tags": [], "restrictions": [], "see_also": [], "antonyms": [], "source": [], "info": []}, {"english_definitions": ["highest (of a three-tier ranking system)"], "parts_of_speech": ["Noun"], "links": [], "tags": [], "restrictions": [], "see_also": ["\u6885 \u3046\u3081", "\u7af9 \u305f\u3051"], "antonyms": [], "source": [], "info": []}, {"english_definitions": ["Pine"], "parts_of_speech": ["Wikipedia definition"], "links": [{"text": "Read \u201cPine\u201d on English Wikipedia", "url": "http://en.wikipedia.org/wiki/Pine?oldid=495326096"}, {"text": "Read \u201c\u30de\u30c4\u201d on Japanese Wikipedia", "url": "http://ja.wikipedia.org/wiki/\u30de\u30c4?oldid=42602683"}], "tags": [], "restrictions": [], "see_also": [], "antonyms": [], "source": [], "info": [], "sentences": []}], "attribution": {"jmdict": true, "jmnedict": false, "dbpedia": "http://dbpedia.org/resource/Pine"}, "id": 3928, "result": null}, {"slug": "\u306f\u3042", "is_common": false, "tags": [], "jlpt": ["jlpt-n3"], "japanese": [{"reading": "\u306f\u3042"}, {"reading": "\u306f\u30fc"}, {"reading": "\u306f"}, {"reading": "\u306f\u3041"}, {"reading": "\u306f\u3042\u3063"}, {"reading": "\u306f\u30fc\u30c3"}, {"reading": "\u30cf\u30fc\u30c3"}], "senses": [{"english_definitions": ["yes", "indeed", "well"], "parts_of_speech": [], "links": [], "tags": [], "restrictions": [], "see_also": [], "antonyms": [], "source": [], "info": []}, {"english_definitions": ["ha!"], "parts_of_speech": [], "links": [], "tags": [], "restrictions": [], "see_also": [], "antonyms": [], "source": [], "info": []}, {"english_definitions": ["what?", "huh?"], "parts_of_speech": [], "links": [], "tags": [], "restrictions": [], "see_also": [], "antonyms": [], "source": [], "info": []}, {"english_definitions": ["sigh"], "parts_of_speech": [], "links": [], "tags": [], "restrictions": [], "see_also": [], "antonyms": [], "source": [], "info": []}], "attribution": {"jmdict": true, "jmnedict": false, "dbpedia": false}, "id": 3929, "result": null}, {"slug": "\u4e0a-3", "is_common": true, "tags": [], "jlpt": ["jlpt-n3"], "japanese": [{"word": "\u4e0a", "reading": "\u3058\u3087\u3046"}], "senses": [{"english_definitions": ["from the standpoint of", "from the viewpoint of", "with respect to", "in terms of", "as a matter of", "in view of", "so far as ... is concerned"], "parts_of_speech": ["Suffix"], "links": [], "tags": [], "restrictions": [], "see_also": [], "antonyms": [], "source": [], "info": []}, {"english_definitions": ["on", "above", "on top of", "aboard (a ship or vehicle)"], "parts_of_speech": ["Suffix"], "links": [], "tags": [], "restrictions": [], "see_also": [], "antonyms": [], "source": [], "info": []}, {"english_definitions": ["the best", "top", "first class", "first grade"], "parts_of_speech": ["Noun", "Noun which may take the genitive case particle 'no'"], "links": [], "tags": [], "restrictions": [], "see_also": [], "antonyms": [], "source": [], "info": []}, {"english_definitions": ["first volume (of a two or three-volume set)", "first book"], "parts_of_speech": ["Noun"], "links": [], "tags": [], "restrictions": [], "see_also": ["\u4e0b", "\u4e2d"], "antonyms": [], "source": [], "info": []}, {"english_definitions": ["with my compliments"], "parts_of_speech": ["Expressions (phrases, clauses, etc.)"], "links": [], "tags": [], "restrictions": [], "see_also": [], "antonyms": [], "source": [], "info": ["written on a gift's wrapping paper"]}], "attribution": {"jmdict": true, "jmnedict": false, "dbpedia": false}, "id": 3930, "result": null}, {"slug": "\u9593-1", "is_common": true, "tags": ["wanikani8"], "jlpt": ["jlpt-n3"], "japanese": [{"word": "\u9593", "reading": "\u307e"}], "senses": [{"english_definitions": ["time", "pause"], "parts_of_speech": ["Noun"], "links": [], "tags": [], "restrictions": [], "see_also": [], "antonyms": [], "source": [], "info": []}, {"english_definitions": ["space"], "parts_of_speech": ["Noun"], "links": [], "tags": [], "restrictions": [], "see_also": [], "antonyms": [], "source": [], "info": []}, {"english_definitions": ["room"], "parts_of_speech": ["Noun"], "links": [], "tags": [], "restrictions": [], "see_also": [], "antonyms": [], "source": [], "info": []}], "attribution": {"jmdict": true, "jmnedict": false, "dbpedia": false}, "id": 3931, "result": null}, {"slug": "\u5f8c-1", "is_common": true, "tags": [], "jlpt": ["jlpt-n3"], "japanese": [{"word": "\u5f8c", "reading": "\u306e\u3061"}], "senses": [{"english_definitions": ["later", "afterwards"], "parts_of_speech": ["Noun", "Adverb (fukushi)", "Noun which may take the genitive case particle 'no'"], "links": [], "tags": ["Usually written using kana alone"], "restrictions": [], "see_also": [], "antonyms": [], "source": [], "info": []}, {"english_definitions": ["future"], "parts_of_speech": ["Noun", "Noun which may take the genitive case particle 'no'"], "links": [], "tags": ["Usually written using kana alone"], "restrictions": [], "see_also": [], "antonyms": [], "source": [], "info": []}, {"english_definitions": ["after one's death"], "parts_of_speech": ["Noun", "Noun which may take the genitive case particle 'no'"], "links": [], "tags": [], "restrictions": [], "see_also": [], "antonyms": [], "source": [], "info": []}, {"english_definitions": ["descendant"], "parts_of_speech": ["Noun"], "links": [], "tags": ["Archaic"], "restrictions": [], "see_also": [], "antonyms": [], "source": [], "info": []}], "attribution": {"jmdict": true, "jmnedict": false, "dbpedia": false}, "id": 3932, "result": null}, {"slug": "\u91d1-1", "is_common": true, "tags": ["wanikani5"], "jlpt": ["jlpt-n3"], "japanese": [{"word": "\u91d1", "reading": "\u304d\u3093"}], "senses": [{"english_definitions": ["gold (metal)"], "parts_of_speech": ["Noun"], "links": [], "tags": [], "restrictions": [], "see_also": [], "antonyms": [], "source": [], "info": []}, {"english_definitions": ["gold (color)"], "parts_of_speech": ["Noun"], "links": [], "tags": [], "restrictions": [], "see_also": ["\u91d1\u8272"], "antonyms": [], "source": [], "info": []}, {"english_definitions": ["gold (medal)", "first place (prize)"], "parts_of_speech": ["Noun"], "links": [], "tags": [], "restrictions": [], "see_also": [], "antonyms": [], "source": [], "info": []}, {"english_definitions": ["something of great value", "something golden (e.g. silence)"], "parts_of_speech": ["Noun", "Noun which may take the genitive case particle 'no'"], "links": [], "tags": [], "restrictions": [], "see_also": [], "antonyms": [], "source": [], "info": []}, {"english_definitions": ["money", "gold coin"], "parts_of_speech": ["Noun"], "links": [], "tags": [], "restrictions": [], "see_also": [], "antonyms": [], "source": [], "info": []}, {"english_definitions": ["sum (of money)"], "parts_of_speech": ["Noun"], "links": [], "tags": [], "restrictions": [], "see_also": [], "antonyms": [], "source": [], "info": ["written before an amount of money"]}, {"english_definitions": ["Friday"], "parts_of_speech": ["Noun"], "links": [], "tags": ["Abbreviation"], "restrictions": [], "see_also": ["\u91d1\u66dc"], "antonyms": [], "source": [], "info": []}, {"english_definitions": ["karat (measure of purity of gold)", "carat"], "parts_of_speech": ["Noun", "Counter"], "links": [], "tags": [], "restrictions": [], "see_also": [], "antonyms": [], "source": [], "info": []}, {"english_definitions": ["metal (fourth phase of Wu Xing)"], "parts_of_speech": ["Noun"], "links": [], "tags": [], "restrictions": [], "see_also": ["\u4e94\u884c"], "antonyms": [], "source": [], "info": []}, {"english_definitions": ["Jin dynasty (of China; 1115-1234)", "Chin dynasty", "Jurchen dynasty"], "parts_of_speech": ["Noun"], "links": [], "tags": ["Historical term"], "restrictions": [], "see_also": [], "antonyms": [], "source": [], "info": []}, {"english_definitions": ["gold general"], "parts_of_speech": ["Noun"], "links": [], "tags": ["Shogi", "Abbreviation"], "restrictions": [], "see_also": ["\u91d1\u5c06"], "antonyms": [], "source": [], "info": []}, {"english_definitions": ["testicles"], "parts_of_speech": ["Noun"], "links": [], "tags": ["Abbreviation", "Colloquial"], "restrictions": [], "see_also": ["\u91d1\u7389"], "antonyms": [], "source": [], "info": []}], "attribution": {"jmdict": true, "jmnedict": false, "dbpedia": false}, "id": 3933, "result": null}, {"slug": "\u91d1", "is_common": true, "tags": [], "jlpt": ["jlpt-n3"], "japanese": [{"word": "\u91d1", "reading": "\u304b\u306d"}, {"word": "\u91d1", "reading": "\u304b\u306a"}], "senses": [{"english_definitions": ["money"], "parts_of_speech": ["Noun"], "links": [], "tags": [], "restrictions": [], "see_also": ["\u304a\u91d1"], "antonyms": [], "source": [], "info": []}, {"english_definitions": ["metal"], "parts_of_speech": ["Noun"], "links": [], "tags": [], "restrictions": [], "see_also": [], "antonyms": [], "source": [], "info": []}], "attribution": {"jmdict": true, "jmnedict": false, "dbpedia": false}, "id": 3934, "result": null}]