{"meta": {"status": 200}, "data": [{"slug": "\u5b9b\u3066\u308b", "is_common": false, "tags": [], "jlpt": ["jlpt-n1"], "japanese": [{"word": "\u5b9b\u3066\u308b", "reading": "\u3042\u3066\u308b"}], "senses": [{"english_definitions": ["to address"], "parts_of_speech": ["Ichidan verb", "Transitive verb"], "links": [], "tags": [], "restrictions": [], "see_also": [], "antonyms": [], "source": [], "info": []}], "attribution": {"jmdict": true, "jmnedict": false, "dbpedia": false}}, {"slug": "\u7167\u308a\u8fd4\u3059", "is_common": false, "tags": [], "jlpt": ["jlpt-n1"], "japanese": [{"word": "\u7167\u308a\u8fd4\u3059", "reading": "\u3066\u308a\u304b\u3048\u3059"}], "senses": [{"english_definitions": ["to reflect", "to throw back light"], "parts_of_speech": ["Godan verb with 'su' ending", "Intransitive verb"], "links": [], "tags": [], "restrictions": [], "see_also": [], "antonyms": [], "source": [], "info": []}], "attribution": {"jmdict": true, "jmnedict": false, "dbpedia": false}}, {"slug": "\u624b\u7b48", "is_common": false, "tags": [], "jlpt": ["jlpt-n1"], "japanese": [{"word": "\u624b\u306f\u305a", "reading": "\u3066\u306f\u305a"}, {"word": "\u624b\u7b48", "reading": "\u3066\u306f\u305a"}], "senses": [{"english_definitions": ["arrangements", "plan", "programme", "program", "preparations"], "parts_of_speech": ["Noun"], "links": [], "tags": [], "restrictions": [], "see_also": [], "antonyms": [], "source": [], "info": []}], "attribution": {"jmdict": true, "jmnedict": false, "dbpedia": false}}, {"slug": "\u6e7f\u6c17\u308b", "is_common": false, "tags": [], "jlpt": ["jlpt-n1"], "japanese": [{"word": "\u6e7f\u6c17\u308b", "reading": "\u3057\u3051\u308b"}, {"word": "\u6e7f\u6c17\u308b", "reading": "\u3057\u3063\u3051\u308b"}], "senses": [{"english_definitions": ["to get damp", "to get moist", "to get soggy", "to become humid"], "parts_of_speech": ["Ichidan verb", "Intransitive verb"], "links": [], "tags": [], "restrictions": [], "see_also": [], "antonyms": [], "source": [], "info": []}], "attribution": {"jmdict": true, "jmnedict": false, "dbpedia": false}}, {"slug": "\u7e8f\u307e\u308a", "is_common": false, "tags": [], "jlpt": ["jlpt-n1"], "japanese": [{"word": "\u7e8f\u307e\u308a", "reading": "\u307e\u3068\u307e\u308a"}], "senses": [{"english_definitions": ["unity", "coherence", "consistency", "coordination", "order"], "parts_of_speech": ["Noun"], "links": [], "tags": ["Usually written using kana alone"], "restrictions": [], "see_also": [], "antonyms": [], "source": [], "info": []}, {"english_definitions": ["settlement", "conclusion", "closure", "completion"], "parts_of_speech": ["Noun"], "links": [], "tags": ["Usually written using kana alone"], "restrictions": [], "see_also": [], "antonyms": [], "source": [], "info": []}], "attribution": {"jmdict": true, "jmnedict": false, "dbpedia": false}}, {"slug": "\u554f", "is_common": true, "tags": [], "jlpt": ["jlpt-n1"], "japanese": [{"word": "\u554f", "reading": "\u3082\u3093"}], "senses": [{"english_definitions": ["counter for questions"], "parts_of_speech": ["Suffix", "Counter"], "links": [], "tags": [], "restrictions": [], "see_also": [], "antonyms": [], "source": [], "info": []}], "attribution": {"jmdict": true, "jmnedict": false, "dbpedia": false}}, {"slug": "\u9244\u7247", "is_common": false, "tags": [], "jlpt": ["jlpt-n1"], "japanese": [{"word": "\u9244\u7247", "reading": "\u3066\u3063\u307a\u3093"}], "senses": [{"english_definitions": ["iron scraps"], "parts_of_speech": ["Noun"], "links": [], "tags": [], "restrictions": [], "see_also": [], "antonyms": [], "source": [], "info": []}], "attribution": {"jmdict": true, "jmnedict": false, "dbpedia": false}}, {"slug": "\u673d\u3061\u308b", "is_common": false, "tags": ["wanikani58"], "jlpt": ["jlpt-n1"], "japanese": [{"word": "\u673d\u3061\u308b", "reading": "\u304f\u3061\u308b"}], "senses": [{"english_definitions": ["to rot", "to decay"], "parts_of_speech": ["Ichidan verb", "Intransitive verb"], "links": [], "tags": [], "restrictions": [], "see_also": [], "antonyms": [], "source": [], "info": []}, {"english_definitions": ["to die in obscurity"], "parts_of_speech": ["Ichidan verb", "Intransitive verb"], "links": [], "tags": [], "restrictions": [], "see_also": [], "antonyms": [], "source": [], "info": []}, {"english_definitions": ["to be forgotten with time"], "parts_of_speech": ["Ichidan verb", "Intransitive verb"], "links": [], "tags": [], "restrictions": [], "see_also": [], "antonyms": [], "source": [], "info": ["often in neg."]}], "attribution": {"jmdict": true, "jmnedict": false, "dbpedia": false}}, {"slug": "\u6293\u308b", "is_common": false, "tags": [], "jlpt": ["jlpt-n1"], "japanese": [{"word": "\u6293\u308b", "reading": "\u3064\u306d\u308b"}, {"word": "\u6293\u308b", "reading": "\u3064\u3081\u308b"}, {"word": "\u6293\u3081\u308b", "reading": "\u3064\u3081\u308b"}], "senses": [{"english_definitions": ["to pinch", "to nip"], "parts_of_speech": ["Godan verb with 'ru' ending", "Transitive verb"], "links": [], "tags": ["Usually written using kana alone"], "restrictions": [], "see_also": [], "antonyms": [], "source": [], "info": []}], "attribution": {"jmdict": true, "jmnedict": false, "dbpedia": false}}, {"slug": "\u5e33-1", "is_common": false, "tags": [], "jlpt": ["jlpt-n1"], "japanese": [{"word": "\u5e33", "reading": "\u3068\u3070\u308a"}, {"word": "\u5e37", "reading": "\u3068\u3070\u308a"}, {"word": "\u5e44", "reading": "\u3068\u3070\u308a"}, {"word": "\u5e4c", "reading": "\u3068\u3070\u308a"}], "senses": [{"english_definitions": ["curtain", "hanging", "bunting"], "parts_of_speech": ["Noun"], "links": [], "tags": ["Usually written using kana alone"], "restrictions": [], "see_also": [], "antonyms": [], "source": [], "info": []}], "attribution": {"jmdict": true, "jmnedict": false, "dbpedia": false}}, {"slug": "\u5bfe\u8fba", "is_common": false, "tags": [], "jlpt": ["jlpt-n1"], "japanese": [{"word": "\u5bfe\u8fba", "reading": "\u305f\u3044\u3078\u3093"}], "senses": [{"english_definitions": ["opposite side"], "parts_of_speech": ["Noun"], "links": [], "tags": ["Mathematics"], "restrictions": [], "see_also": [], "antonyms": [], "source": [], "info": []}], "attribution": {"jmdict": true, "jmnedict": false, "dbpedia": false}}, {"slug": "\u99c4\u4f5c", "is_common": false, "tags": [], "jlpt": ["jlpt-n1"], "japanese": [{"word": "\u99c4\u4f5c", "reading": "\u3060\u3055\u304f"}], "senses": [{"english_definitions": ["poor piece of work", "rubbish", "trash"], "parts_of_speech": ["Noun"], "links": [], "tags": [], "restrictions": [], "see_also": [], "antonyms": [], "source": [], "info": []}], "attribution": {"jmdict": true, "jmnedict": false, "dbpedia": false}}, {"slug": "\u8f9f\u6613", "is_common": false, "tags": [], "jlpt": ["jlpt-n1"], "japanese": [{"word": "\u8f9f\u6613", "reading": "\u3078\u304d\u3048\u304d"}, {"reading": "\u30d8\u30ad\u30a8\u30ad"}], "senses": [{"english_definitions": ["to be fed up (with)", "to be tired (of)", "to be bored (with)", "to be unable to bear"], "parts_of_speech": ["Suru verb", "Intransitive verb", "Noun"], "links": [], "tags": [], "restrictions": [], "see_also": [], "antonyms": [], "source": [], "info": []}, {"english_definitions": ["to be stumped", "to be nonplussed", "to be disconcerted"], "parts_of_speech": ["Suru verb", "Intransitive verb", "Noun"], "links": [], "tags": [], "restrictions": [], "see_also": [], "antonyms": [], "source": [], "info": []}, {"english_definitions": ["to wince", "to shrink back", "to cringe"], "parts_of_speech": ["Suru verb", "Intransitive verb", "Noun"], "links": [], "tags": [], "restrictions": [], "see_also": [], "antonyms": [], "source": [], "info": []}], "attribution": {"jmdict": true, "jmnedict": false, "dbpedia": false}}, {"slug": "\u865a\u308d", "is_common": false, "tags": [], "jlpt": ["jlpt-n1"], "japanese": [{"word": "\u865a\u308d", "reading": "\u3046\u3064\u308d"}, {"word": "\u7a7a\u308d", "reading": "\u3046\u3064\u308d"}, {"word": "\u6d1e\u308d", "reading": "\u3046\u3064\u308d"}, {"word": "\u6d1e", "reading": "\u3046\u3064\u308d"}], "senses": [{"english_definitions": ["cavity", "hollow", "void"], "parts_of_speech": ["Noun", "Na-adjective (keiyodoshi)"], "links": [], "tags": [], "restrictions": [], "see_also": [], "antonyms": [], "source": [], "info": []}, {"english_definitions": ["hollow (voice, smile, etc.)", "blank (eyes, look, etc.)", "vacant (expression, stare, etc.)", "empty (words, heart, etc.)"], "parts_of_speech": ["Na-adjective (keiyodoshi)"], "links": [], "tags": [], "restrictions": ["\u865a\u308d", "\u7a7a\u308d"], "see_also": [], "antonyms": [], "source": [], "info": []}], "attribution": {"jmdict": true, "jmnedict": false, "dbpedia": false}}, {"slug": "\u5d69\u3080", "is_common": false, "tags": [], "jlpt": ["jlpt-n1"], "japanese": [{"word": "\u5d69\u3080", "reading": "\u304b\u3055\u3080"}], "senses": [{"english_definitions": ["to mount up", "to pile up", "to accumulate", "to increase"], "parts_of_speech": ["Godan verb with 'mu' ending", "Intransitive verb"], "links": [], "tags": ["Usually written using kana alone"], "restrictions": [], "see_also": [], "antonyms": [], "source": [], "info": []}], "attribution": {"jmdict": true, "jmnedict": false, "dbpedia": false}}, {"slug": "\u6c5a\u3089\u308f\u3057\u3044", "is_common": false, "tags": [], "jlpt": ["jlpt-n1"], "japanese": [{"word": "\u6c5a\u3089\u308f\u3057\u3044", "reading": "\u3051\u304c\u3089\u308f\u3057\u3044"}, {"word": "\u7a62\u3089\u308f\u3057\u3044", "reading": "\u3051\u304c\u3089\u308f\u3057\u3044"}], "senses": [{"english_definitions": ["filthy", "unfair", "dirty", "untouchable", "disgusting", "nasty", "foul", "odious", "repulsive"], "parts_of_speech": ["I-adjective (keiyoushi)"], "links": [], "tags": [], "restrictions": [], "see_also": [], "antonyms": [], "source": [], "info": []}], "attribution": {"jmdict": true, "jmnedict": false, "dbpedia": false}}, {"slug": "\u306d\u3058\u56de\u3057", "is_common": false, "tags": [], "jlpt": ["jlpt-n1"], "japanese": [{"word": "\u306d\u3058\u56de\u3057", "reading": "\u306d\u3058\u307e\u308f\u3057"}, {"word": "\u30cd\u30b8\u56de\u3057", "reading": "\u306d\u3058\u307e\u308f\u3057"}, {"word": "\u87ba\u5b50\u56de\u3057", "reading": "\u306d\u3058\u307e\u308f\u3057"}], "senses": [{"english_definitions": ["screwdriver"], "parts_of_speech": ["Noun"], "links": [], "tags": [], "restrictions": [], "see_also": ["\u30c9\u30e9\u30a4\u30d0\u30fc"], "antonyms": [], "source": [], "info": []}], "attribution": {"jmdict": true, "jmnedict": false, "dbpedia": false}}, {"slug": "\u304a\u5bae", "is_common": false, "tags": [], "jlpt": ["jlpt-n1"], "japanese": [{"word": "\u304a\u5bae", "reading": "\u304a\u307f\u3084"}], "senses": [{"english_definitions": ["Shinto shrine"], "parts_of_speech": ["Noun"], "links": [], "tags": [], "restrictions": [], "see_also": [], "antonyms": [], "source": [], "info": []}], "attribution": {"jmdict": true, "jmnedict": false, "dbpedia": false}}, {"slug": "\u7d21\u7e3e", "is_common": true, "tags": ["wanikani59"], "jlpt": ["jlpt-n1"], "japanese": [{"word": "\u7d21\u7e3e", "reading": "\u307c\u3046\u305b\u304d"}], "senses": [{"english_definitions": ["spinning (textiles)"], "parts_of_speech": ["Noun"], "links": [], "tags": [], "restrictions": [], "see_also": [], "antonyms": [], "source": [], "info": []}, {"english_definitions": ["spun yarn"], "parts_of_speech": ["Noun"], "links": [], "tags": ["Abbreviation"], "restrictions": [], "see_also": ["\u7d21\u7e3e\u7cf8"], "antonyms": [], "source": [], "info": []}, {"english_definitions": ["Spinning (textiles)"], "parts_of_speech": ["Wikipedia definition"], "links": [{"text": "Read \u201cSpinning (textiles)\u201d on English Wikipedia", "url": "http://en.wikipedia.org/wiki/Spinning_(textiles)?oldid=493105928"}, {"text": "Read \u201c\u7d21\u7e3e\u201d on Japanese Wikipedia", "url": "http://ja.wikipedia.org/wiki/\u7d21\u7e3e?oldid=42721678"}], "tags": [], "restrictions": [], "see_also": [], "antonyms": [], "source": [], "info": [], "sentences": []}], "attribution": {"jmdict": true, "jmnedict": false, "dbpedia": "http://dbpedia.org/resource/Spinning_(textiles)"}}, {"slug": "\u914d\u5217", "is_common": true, "tags": [], "jlpt": ["jlpt-n1"], "japanese": [{"word": "\u914d\u5217", "reading": "\u306f\u3044\u308c\u3064"}, {"word": "\u6392\u5217", "reading": "\u306f\u3044\u308c\u3064"}], "senses": [{"english_definitions": ["arranging", "ordering", "sequencing", "lining up", "laying out"], "parts_of_speech": ["Noun", "Suru verb", "Transitive verb"], "links": [], "tags": [], "restrictions": [], "see_also": [], "antonyms": [], "source": [], "info": []}, {"english_definitions": ["sequence (e.g. DNA sequence)", "arrangement", "alignment", "layout (e.g. keyboard layout)"], "parts_of_speech": ["Noun", "Noun, used as a suffix"], "links": [], "tags": [], "restrictions": [], "see_also": [], "antonyms": [], "source": [], "info": []}, {"english_definitions": ["array"], "parts_of_speech": ["Noun"], "links": [], "tags": ["Computing"], "restrictions": ["\u914d\u5217"], "see_also": [], "antonyms": [], "source": [], "info": []}, {"english_definitions": ["Array data structure"], "parts_of_speech": ["Wikipedia definition"], "links": [{"text": "Read \u201cArray data structure\u201d on English Wikipedia", "url": "http://en.wikipedia.org/wiki/Array_data_structure?oldid=492568770"}, {"text": "Read \u201c\u914d\u5217\u201d on Japanese Wikipedia", "url": "http://ja.wikipedia.org/wiki/\u914d\u5217?oldid=41368365"}], "tags": [], "restrictions": [], "see_also": [], "antonyms": [], "source": [], "info": [], "sentences": []}], "attribution": {"jmdict": true, "jmnedict": false, "dbpedia": "http://dbpedia.org/resource/Array_data_structure"}}]}