[{"slug": "\u8a82\u3048\u308b", "is_common": false, "tags": [], "jlpt": ["jlpt-n1"], "japanese": [{"word": "\u8a82\u3048\u308b", "reading": "\u3042\u3064\u3089\u3048\u308b"}], "senses": [{"english_definitions": ["to give an order", "to place an order", "to have made to order"], "parts_of_speech": ["Ichidan verb", "Transitive verb"], "links": [], "tags": ["Usually written using kana alone"], "restrictions": [], "see_also": [], "antonyms": [], "source": [], "info": []}], "attribution": {"jmdict": true, "jmnedict": false, "dbpedia": false}, "id": 2575, "result": null}, {"slug": "\u96e3\u3044", "is_common": false, "tags": [], "jlpt": ["jlpt-n1"], "japanese": [{"word": "\u96e3\u3044", "reading": "\u304b\u305f\u3044"}], "senses": [{"english_definitions": ["difficult", "hard"], "parts_of_speech": ["I-adjective (keiyoushi)"], "links": [], "tags": [], "restrictions": [], "see_also": [], "antonyms": [], "source": [], "info": []}], "attribution": {"jmdict": true, "jmnedict": false, "dbpedia": false}, "id": 2586, "result": null}, {"slug": "\u4e08", "is_common": true, "tags": [], "jlpt": ["jlpt-n1"], "japanese": [{"word": "\u4e08", "reading": "\u3060\u3051"}], "senses": [{"english_definitions": ["only", "just", "merely", "simply", "no more than", "nothing but", "alone"], "parts_of_speech": ["Particle"], "links": [], "tags": ["Usually written using kana alone"], "restrictions": [], "see_also": [], "antonyms": [], "source": [], "info": []}, {"english_definitions": ["as much as", "to the extent of", "enough to"], "parts_of_speech": ["Particle"], "links": [], "tags": ["Usually written using kana alone"], "restrictions": [], "see_also": [], "antonyms": [], "source": [], "info": []}], "attribution": {"jmdict": true, "jmnedict": false, "dbpedia": false}, "id": 2587, "result": null}, {"slug": "\u306a\u3093\u304b", "is_common": true, "tags": [], "jlpt": ["jlpt-n1"], "japanese": [{"reading": "\u306a\u3093\u304b"}], "senses": [{"english_definitions": ["something like ...", "things like ...", "someone like ...", "the likes of ..."], "parts_of_speech": ["Particle", "Adverb (fukushi)"], "links": [], "tags": [], "restrictions": [], "see_also": [], "antonyms": [], "source": [], "info": ["oft. scornful or dismissive"]}], "attribution": {"jmdict": true, "jmnedict": false, "dbpedia": false}, "id": 2588, "result": null}, {"slug": "\u304f\u3089\u3044", "is_common": true, "tags": [], "jlpt": ["jlpt-n1"], "japanese": [{"reading": "\u304f\u3089\u3044"}, {"reading": "\u3050\u3089\u3044"}], "senses": [{"english_definitions": ["approximately", "about", "around", "or so"], "parts_of_speech": ["Suffix", "Particle"], "links": [], "tags": [], "restrictions": [], "see_also": [], "antonyms": [], "source": [], "info": ["also written as \u4f4d"]}, {"english_definitions": ["to (about) the extent that", "(almost) enough that", "so ... that ...", "at least"], "parts_of_speech": ["Suffix", "Particle"], "links": [], "tags": [], "restrictions": [], "see_also": [], "antonyms": [], "source": [], "info": []}, {"english_definitions": ["as ... as ...", "like"], "parts_of_speech": ["Suffix", "Particle"], "links": [], "tags": [], "restrictions": [], "see_also": [], "antonyms": [], "source": [], "info": []}], "attribution": {"jmdict": true, "jmnedict": false, "dbpedia": false}, "id": 2589, "result": null}, {"slug": "\u30aa\u30ec\u30f3\u30b8", "is_common": true, "tags": [], "jlpt": ["jlpt-n1"], "japanese": [{"reading": "\u30aa\u30ec\u30f3\u30b8"}], "senses": [{"english_definitions": ["orange (fruit, colour)"], "parts_of_speech": ["Noun", "Noun which may take the genitive case particle 'no'"], "links": [], "tags": [], "restrictions": [], "see_also": [], "antonyms": [], "source": [], "info": []}, {"english_definitions": ["Orange"], "parts_of_speech": ["Place"], "links": [], "tags": [], "restrictions": [], "see_also": [], "antonyms": [], "source": [], "info": []}, {"english_definitions": ["Orange (fruit)"], "parts_of_speech": ["Wikipedia definition"], "links": [{"text": "Read \u201cOrange (fruit)\u201d on English Wikipedia", "url": "http://en.wikipedia.org/wiki/Orange_(fruit)?oldid=493877484"}, {"text": "Read \u201c\u30aa\u30ec\u30f3\u30b8\u201d on Japanese Wikipedia", "url": "http://ja.wikipedia.org/wiki/\u30aa\u30ec\u30f3\u30b8?oldid=42636201"}], "tags": [], "restrictions": [], "see_also": [], "antonyms": [], "source": [], "info": [], "sentences": []}], "attribution": {"jmdict": true, "jmnedict": true, "dbpedia": "http://dbpedia.org/resource/Orange_(fruit)"}, "id": 2590, "result": null}]